encoder_converter/__init__.py
encoder_converter/args.py
encoder_converter/cli.py
encoder_converter/core.py
encoder_converter/wrappers.py
encoder_converter-0.2.0.dist-info/METADATA
encoder_converter-0.2.0.dist-info/WHEEL
encoder_converter-0.2.0.dist-info/entry_points.txt
encoder_converter-0.2.0.dist-info/RECORD
