Metadata-Version: 2.3
Name: encoder-converter
Version: 0.2.0
Summary: Convert huggingface encoder to onnx format.
Author: aveitsme
Author-email: aveitsme@gmail.com
Requires-Python: >=3.10,<3.13
Classifier: Programming Language :: Python :: 3
Classifier: Programming Language :: Python :: 3.10
Classifier: Programming Language :: Python :: 3.11
Classifier: Programming Language :: Python :: 3.12
Requires-Dist: onnx (>=1.0.0,<2.0.0)
Requires-Dist: onnxruntime (>=1.0.0,<2.0.0)
Requires-Dist: openvino (>=2025.1.0,<2026.0.0)
Requires-Dist: tokenizers (>=0.2.0,<1.0.0)
Requires-Dist: torch (>=2.0.0,<3.0.0)
Requires-Dist: transformers (>=4.0.0,<5.0.0)
Project-URL: Homepage, https://github.com/AVEitsme/encoder-converter
Project-URL: Repository, https://github.com/AVEitsme/encoder-converter
